plugs_core/__init__.py
plugs_core/apps.py
plugs_core/clients.py
plugs_core/fields.py
plugs_core/mixins.py
plugs_core/permissions.py
plugs_core/serializers.py
plugs_core/testcases.py
plugs_core/urls.py
plugs_core/utils.py
plugs_core/validators.py
plugs_core/viewsets.py
plugs_core-0.2.1.dist-info/AUTHORS.rst
plugs_core-0.2.1.dist-info/LICENSE
plugs_core-0.2.1.dist-info/METADATA
plugs_core-0.2.1.dist-info/WHEEL
plugs_core-0.2.1.dist-info/top_level.txt
plugs_core-0.2.1.dist-info/RECORD
