Metadata-Version: 2.1
Name: plugs-core
Version: 0.2.1
Summary: Reusable Core APP
Home-page: https://github.com/solocompt/plugs-core
Author: Solo
Author-email: geral@solo.com.pt
License: MIT
Keywords: plugs-core
Platform: UNKNOWN
Classifier: Development Status :: 3 - Alpha
Classifier: Framework :: Django :: 1.11
Classifier: Intended Audience :: Developers
Classifier: License :: OSI Approved :: MIT License
Classifier: Natural Language :: English
Classifier: Programming Language :: Python :: 3
Requires-Dist: django (<3.0.0,>=1.9.7)
Requires-Dist: djangorestframework (<4.0.0,>=3.6.4)
Requires-Dist: djangorestframework-jwt
Requires-Dist: lxml (>=4.1.2)
